saranglebah/__init__.py
saranglebah/__main__.py
saranglebah/cli.py
saranglebah/logger.py
saranglebah/master.py
saranglebah/slave.py
saranglebah-0.1.5.dist-info/licenses/LICENSE
saranglebah-0.1.5.dist-info/METADATA
saranglebah-0.1.5.dist-info/WHEEL
saranglebah-0.1.5.dist-info/entry_points.txt
saranglebah-0.1.5.dist-info/top_level.txt
saranglebah-0.1.5.dist-info/RECORD
