Metadata-Version: 2.4
Name: saranglebah
Version: 0.1.5
Summary: Broadcast keystrokes from a master PC to multiple slaves over Wi‑Fi
Author: 
Classifier: Programming Language :: Python :: 3
Classifier: License :: OSI Approved :: MIT License
Classifier: Operating System :: OS Independent
Requires-Python: >=3.7
License-File: LICENSE
Requires-Dist: pynput>=1.7
Dynamic: classifier
Dynamic: license-file
Dynamic: requires-dist
Dynamic: requires-python
Dynamic: summary
